docs/conf.py
src/packages/__init__.py
src/packages/sparsity.py
leden-0.0.2.dist-info/METADATA
leden-0.0.2.dist-info/WHEEL
leden-0.0.2.dist-info/licenses/LICENSE
leden-0.0.2.dist-info/RECORD
