Metadata-Version: 2.1
Name: LEDEN
Version: 0.0.2
Summary: A library to calculate quality metrics on explanations produced by explainers for the decisions of binary classifiers.
Project-URL: Homepage, https://github.com/casper2015/LEDEN
Author-email: Mihir Rao <raomihir.98@gmail.com>
License-File: LICENSE
Classifier: License :: OSI Approved :: MIT License
Classifier: Operating System :: OS Independent
Classifier: Programming Language :: Python :: 3
Requires-Python: >=3.7
